{
  "date": "2026-01-27",
  "calculation_time": "2026-01-27 07:32:18",
  "exchange_rates": {
    "usd_ngn": 1502.1504,
    "usd_cny": 6.9544,
    "cny_ngn": 216,
    "cny_ngn_source": "Manual Override"
  },
  "parameters": {
    "vat_rate": 1.13,
    "logistics_cost_sea_ngn": 80309,
    "coltan_air_cost_usd": 8,
    "spodumene_discount": 0.3,
    "lepidolite_discount": 0.3
  },
  "source_prices": {
    "tin": {
      "price": 54361.21,
      "unit": "USD/mt"
    },
    "tantalum_oxide": {
      "price": 314.06,
      "unit": "USD/kg"
    },
    "monazite": {
      "price": null,
      "unit": "USD/mt"
    },
    "titanium": {
      "price": null,
      "unit": "CNY/mt"
    },
    "zircon": {
      "price": 1744.79,
      "unit": "USD/mt"
    },
    "spodumene": {
      "price": 2205.0,
      "unit": "USD/mt"
    },
    "lithium_carbonate": {
      "price": 21889.14,
      "unit": "USD/mt"
    },
    "lead": {
      "price": 2138.16,
      "unit": "USD/mt"
    },
    "zinc": {
      "price": 3141.88,
      "unit": "USD/mt"
    }
  },
  "max_purchase_prices": {
    "tin_ore": {
      "unit": "NGN/kg",
      "base_grade": "70%",
      "grades": {
        "60%": 43288.0,
        "61%": 44010.0,
        "62%": 44733.0,
        "63%": 45455.0,
        "64%": 46178.0,
        "65%": 46901.0,
        "66%": 47623.0,
        "67%": 48346.0,
        "68%": 49069.0,
        "69%": 49791.0,
        "70%": 50514.0
      }
    },
    "coltan": {
      "unit": "NGN/kg",
      "base_grade": "30% Ta₂O₅",
      "note": "Air freight",
      "grades": {
        "20%": 81371.0,
        "25%": 101714.0,
        "30%": 122057.0,
        "35%": 142400.0
      }
    },
    "monazite": {
      "unit": "NGN/kg",
      "base_grade": "60% TREO",
      "grades": {
        "30%": 5095.0,
        "40%": 6817.0,
        "45%": 7678.0,
        "50%": 8539.0,
        "60%": 10261.0
      }
    },
    "titanium": {
      "unit": "NGN/ton",
      "base_grade": "≥50% TiO₂",
      "grades": {
        "50%": 0
      }
    },
    "zircon": {
      "unit": "NGN/ton",
      "base_grade": "≥65% Zr(Hf)O₂",
      "grades": {
        "65%": 2248343.0
      }
    },
    "spodumene": {
      "unit": "NGN/ton",
      "base_grade": "6% Li₂O",
      "grades": {
        "3%": 418357.0,
        "4%": 564916.0,
        "5%": 711476.0,
        "6%": 858035.0
      }
    },
    "lepidolite": {
      "unit": "NGN/ton",
      "base_grade": "2.5% Li₂O",
      "grades": {
        "2.0%": 224634.0,
        "2.5%": 286123.0,
        "3.0%": 347612.0
      }
    },
    "lead_ore": {
      "unit": "NGN/ton",
      "base_grade": "50% Pb",
      "grades": {
        "40%": 1065864.0,
        "50%": 1350097.0,
        "60%": 1634331.0
      }
    },
    "zinc_ore": {
      "unit": "NGN/ton",
      "base_grade": "50% Zn",
      "grades": {
        "40%": 1599577.0,
        "50%": 2017238.0,
        "60%": 2434900.0
      }
    }
  }
}